LICENSE.txt
MANIFEST.in
README.rst
pyproject.toml
setup.cfg
setup.py
PyPika.egg-info/PKG-INFO
PyPika.egg-info/SOURCES.txt
PyPika.egg-info/dependency_links.txt
PyPika.egg-info/top_level.txt
pypika/__init__.py
pypika/analytics.py
pypika/dialects.py
pypika/enums.py
pypika/functions.py
pypika/pseudocolumns.py
pypika/queries.py
pypika/terms.py
pypika/utils.py
pypika/clickhouse/__init__.py
pypika/clickhouse/array.py
pypika/clickhouse/condition.py
pypika/clickhouse/dates_and_times.py
pypika/clickhouse/nullable_arg.py
pypika/clickhouse/search_string.py
pypika/clickhouse/type_conversion.py